gogh/__init__.py
gogh-0.1.0.dist-info/WHEEL
gogh-0.1.0.dist-info/METADATA
gogh-0.1.0.dist-info/RECORD
