Metadata-Version: 2.1
Name: gogh
Version: 0.1.0
Summary: Brush stroke drawing utility
Author: Enrico Borba
Author-email: enricozb@gmail.com
Requires-Python: >=3.8,<4.0
Classifier: Programming Language :: Python :: 3
Classifier: Programming Language :: Python :: 3.8
